{"inkVersion":21,"root":[[{"->":"JANE_DOE"},["done",{"#f":5,"#n":"g-0"}],null],"done",{"start":["^You wake up as John Doe and find that your son, Johnny Doe, is gone.","\n",{"->":"JANE_DOE"},{"#f":1}],"JANE_DOE":[["^You finally woke up, Johnny didnt come home yet! He said he would be back by morning but its already noon.","\n","ev","str","^I am sure he's fine. Where was he last night?","/str",{"VAR?":"johnny_missing"},"/ev",{"*":".^.c-0","flg":5},{"c-0":["^ He was out with Carl all day and slept at his house slept at Carl's. Johnny said he would be back by the morning","\n",["ev","str","^Where does Carl live again?","/str","/ev",{"*":".^.c-0","flg":4},{"c-0":["^ the house with the red door. ","\n",["ev","str","^Ok, I will bring him home","/str","/ev",{"*":".^.c-0","flg":4},{"c-0":["^ ","done","\n",{"#f":5}]}],{"#f":5}]}],{"#f":5}]}],{"#f":1}],"CARL":[["ev",true,"/ev",{"VAR=":"carl_spoken_to","re":true},"^You find Carl sitting near the market. He looks nervous.","\n","^\"You look like you’ve seen a ghost,\" you say.","\n","ev","str","^\"Where is Johnny?\"","/str","/ev",{"*":".^.c-0","flg":4},{"c-0":["^ ","\n","^Carl sighs. \"He… he joined a gang. They needed an extra hand for a robbery.\"","\n",{"->":"carl_explains"},{"#f":5}]}],{"#f":1}],"carl_explains":[["^Carl looks around before whispering.","\n","^\"The robbery went wrong. Everyone ran when the royal knights arrived. I don’t know where Johnny went, but I swear I didn't mean to get him involved!\"","\n","ev","str","^\"So you're telling me my son is missing?\"","/str","/ev",{"*":".^.c-0","flg":4},"ev","str","^\"You’re a coward! You left him behind!\"","/str","/ev",{"*":".^.c-1","flg":4},{"c-0":["^ ","\n","^\"Yes… but I can help you find him!\" Carl insists.","\n",{"->":"encounter_knights"},{"#f":5}],"c-1":["\n","^Carl flinches. \"I know! I know! I screwed up, okay?\"","\n",{"->":"encounter_knights"},{"#f":5}]}],{"#f":1}],"decide_next_step":[["^Now you need to find Johnny. There are two ways:","\n",["ev",{"^->":"decide_next_step.0.2.$r1"},{"temp=":"$r"},"str",{"->":".^.s"},[{"#n":"$r1"}],"/str","str","^Ask Maximus for help","/str","/ev",{"*":".^.^.c-0","flg":6},{"s":["#","^sticky ","/#",{"->":"$r","var":true},null]}],["ev",{"^->":"decide_next_step.0.3.$r1"},{"temp=":"$r"},"str",{"->":".^.s"},[{"#n":"$r1"}],"/str","str","^Seek help from Captain Rex","/str","/ev",{"*":".^.^.c-1","flg":6},{"s":["#","^sticky ","/#",{"->":"$r","var":true},null]}],{"c-0":["ev",{"^->":"decide_next_step.0.c-0.$r2"},"/ev",{"temp=":"$r"},{"->":".^.^.2.s"},[{"#n":"$r2"}],"^ ",{"->":"talk_to_maximus"},"\n",{"#f":5}],"c-1":["ev",{"^->":"decide_next_step.0.c-1.$r2"},"/ev",{"temp=":"$r"},{"->":".^.^.3.s"},[{"#n":"$r2"}],"^ ",{"->":"talk_to_captain_rex"},"\n",{"#f":5}]}],{"#f":1}],"encounter_knights":[["^As you walk away, two royal knights stop you.","\n","^\"Why were you speaking with Carl?\" one demands.","\n","^\"We know he took part in the robbery. He is a criminal, and we are here to kill him.\"","\n","ev","str","^Let them kill Carl","/str","/ev",{"*":".^.c-0","flg":4},"ev","str","^Defend Carl","/str","/ev",{"*":".^.c-1","flg":4},{"c-0":["^ ","\n","ev",true,"/ev",{"VAR=":"carl_dead","re":true},"^Carl’s eyes widen as the knights cut him down.","\n","^\"Justice is served,\" one knight says before leaving.","\n",{"->":"seek_captain_rex_or_maximus"},{"#f":5}],"c-1":["^ ","\n","ev",true,"/ev",{"VAR=":"knights_hostile","re":true},"^You step between Carl and the knights.","\n","^\"He's just a kid! He didn't plan the robbery!\" you argue.","\n","^\"That makes you a criminal, too,\" the knight sneers.","\n",{"->":"fight_knights"},{"#f":5}]}],{"#f":1}],"fight_knights":["^The knights draw their swords. You have no choice but to fight.","\n","^(Combat happens in Unity)","\n",{"->":"seek_captain_rex_or_maximus"},{"#f":1}],"seek_captain_rex_or_maximus":[["^You need allies. Who do you approach?","\n","ev","str","^Captain Rex","/str","/ev",{"*":".^.c-0","flg":4},"ev","str","^Maximus","/str","/ev",{"*":".^.c-1","flg":4},{"c-0":["^ ",{"->":"talk_to_captain_rex"},"\n",{"#f":5}],"c-1":["^ ",{"->":"talk_to_maximus"},"\n",{"#f":5}]}],{"#f":1}],"talk_to_captain_rex":[["^\"You say the gang took your son? And you expect me to let a peasant hunt criminals?\"","\n","^Captain Rex crosses his arms.","\n","ev","str","^\"I can handle myself.\"","/str","/ev",{"*":".^.c-0","flg":4},"ev","str","^\"I just need information!\"","/str","/ev",{"*":".^.c-1","flg":4},{"c-0":["\n","^\"Prove it. Kill three trolls, and I might help you.\"","\n",{"->":"prove_yourself_to_rex"},{"#f":5}],"c-1":["\n","^\"Information isn’t free. Earn it.\"","\n",{"->":"prove_yourself_to_rex"},{"#f":5}]}],{"#f":1}],"prove_yourself_to_rex":["ev",{"VAR?":"captain_rex_helping"},false,"==","/ev",[{"->":".^.b","c":true},{"b":["\n","^\"If you want my help, complete a task for me first,\" Captain Rex commands.","\n",{"->":".^.^.^.6"},null]}],"nop","\n","end",{"#f":1}],"talk_to_maximus":[["^You meet Maximus in the alley behind the tavern.","\n","^\"I heard about Johnny. The gang's been lurking near the forest.\"","\n","ev","str","^\"Will you help me find them?\"","/str","/ev",{"*":".^.c-0","flg":4},{"c-0":["\n","^\"I could… if I get something in return.\"","\n","end",{"#f":5}]}],{"#f":1}],"global decl":["ev",true,{"VAR=":"johnny_missing"},false,{"VAR=":"carl_spoken_to"},false,{"VAR=":"carl_dead"},false,{"VAR=":"maximus_helping"},false,{"VAR=":"captain_rex_helping"},false,{"VAR=":"knights_hostile"},"/ev","end",null],"#f":1}],"listDefs":{}}